litecore/__init__.py
litecore/__pycache__/__init__.cpython-37.pyc
litecore-0.2.0.dist-info/LICENSE
litecore-0.2.0.dist-info/METADATA
litecore-0.2.0.dist-info/WHEEL
litecore-0.2.0.dist-info/top_level.txt
litecore-0.2.0.dist-info/RECORD
